genetic_functions.cp38-win_amd64.pyd
darwyn/__init__.py
darwyn/genopt/__init__.py
darwyn/genopt/core.py
darwyn/genopt/simulated_annealing.py
darwyn_genopt_kevinlioi-1.1.0.dist-info/METADATA
darwyn_genopt_kevinlioi-1.1.0.dist-info/WHEEL
darwyn_genopt_kevinlioi-1.1.0.dist-info/top_level.txt
darwyn_genopt_kevinlioi-1.1.0.dist-info/RECORD
